contributor_network/__init__.py
contributor_network/cli.py
contributor_network/graph.py
contributor_network/utils.py
contributor_network-0.1.0.dist-info/LICENSE
contributor_network-0.1.0.dist-info/METADATA
contributor_network-0.1.0.dist-info/WHEEL
contributor_network-0.1.0.dist-info/top_level.txt
contributor_network-0.1.0.dist-info/RECORD
