Metadata-Version: 2.1
Name: contributor-network
Version: 0.1.0
Summary: Create an interactive contributor network graph from git/hg repository
Home-page: https://github.com/pythoniccafe/contributor-network/
Author: Álvaro Justen
Author-email: alvarojusten@gmail.com
License: UNKNOWN
Keywords: free-software open-source contributor graph network
Platform: UNKNOWN
Classifier: Intended Audience :: Developers
Classifier: License :: OSI Approved :: GNU Lesser General Public License v3 or later (LGPLv3+)
Classifier: Natural Language :: English
Classifier: Operating System :: OS Independent
Classifier: Programming Language :: Python :: 3.8
Classifier: Topic :: Software Development :: Libraries :: Python Modules
Classifier: Topic :: Utilities
Requires-Python: >=3.8
Requires-Dist: lxml
Requires-Dist: tqdm
